secure_bot/Secure.py
secure_bot/__init__.py
secure_bot-1.0.dist-info/METADATA
secure_bot-1.0.dist-info/WHEEL
secure_bot-1.0.dist-info/top_level.txt
secure_bot-1.0.dist-info/RECORD
