Metadata-Version: 2.1
Name: secure-bot
Version: 1.0
Summary: A secure bot package
Author: K-233
Author-email: shellcloud18@gmail.com
Requires-Dist: telebot
Requires-Dist: requests
